pol_inv/__init__.py
pol_inv/equations.py
pol_inv/errors.py
pol_inv/relational_structure.py
pol_inv/sat_translator.py
pol_inv/solver_callers.py
pol_inv/terms_and_operations.py
pol_inv-0.1.2.dist-info/LICENSE
pol_inv-0.1.2.dist-info/METADATA
pol_inv-0.1.2.dist-info/WHEEL
pol_inv-0.1.2.dist-info/top_level.txt
pol_inv-0.1.2.dist-info/RECORD
