Metadata-Version: 2.1
Name: pol-inv
Version: 0.1.2
Summary: Package for computing polymorphisms in universal algebra
Home-page: https://github.com/alex-kazda/pol-inv
Author: Alexandr Kazda
Author-email: alex.kazda@gmail.com
Classifier: Programming Language :: Python :: 3
Classifier: License :: OSI Approved :: MIT License
Classifier: Operating System :: OS Independent
License-File: LICENSE
Requires-Dist: python-sat
